common/__init__.py
common/decos.py
common/descriptors.py
common/errors.py
common/metaclasses.py
common/utils.py
common/variables.py
logs/__init__.py
logs/server_log_config.py
server/__init__.py
server/add_user.py
server/configuration_window.py
server/core.py
server/history_window.py
server/main_window.py
server/remove_user.py
server/server_database.py
Byunichenko_DB_and_PyQt_server_module-0.0.1.dist-info/METADATA
Byunichenko_DB_and_PyQt_server_module-0.0.1.dist-info/WHEEL
Byunichenko_DB_and_PyQt_server_module-0.0.1.dist-info/top_level.txt
Byunichenko_DB_and_PyQt_server_module-0.0.1.dist-info/RECORD
