Metadata-Version: 2.1
Name: Byunichenko-DB-and-PyQt-server-module
Version: 0.0.1
Summary: message_server_app
Home-page: UNKNOWN
Author: Byunichenko Mikhail
Author-email: mbuinichienko@mail.ru
License: UNKNOWN
Platform: UNKNOWN
Requires-Dist: PyQt5
Requires-Dist: sqlalchemy
Requires-Dist: pycryptodome
Requires-Dist: pycryptodomex
